main.py
pyIAAS/__init__.py
pyIAAS/run.py
pyIAAS/agent/Agent.py
pyIAAS/agent/__init__.py
pyIAAS/agent/components.py
pyIAAS/agent/memory.py
pyIAAS/env/NasEnv.py
pyIAAS/env/__init__.py
pyIAAS/model/__init__.py
pyIAAS/model/model.py
pyIAAS/model/module.py
pyIAAS/utils/__init__.py
pyIAAS/utils/config.py
pyIAAS/utils/data_process.py
pyIAAS/utils/logger.py
pyIAAS/utils/object_dict.py
pyIAAS/utils/sql_connector.py
pyIAAS-0.0.2.dist-info/LICENSE
pyIAAS-0.0.2.dist-info/METADATA
pyIAAS-0.0.2.dist-info/WHEEL
pyIAAS-0.0.2.dist-info/entry_points.txt
pyIAAS-0.0.2.dist-info/top_level.txt
pyIAAS-0.0.2.dist-info/RECORD
