Metadata-Version: 2.1
Name: pyIAAS
Version: 0.0.2
Summary: Code of IAAS Framework
Home-page: https://github.com/JasonloveDL/pyIAAS
Author: JasonLoveDL
Author-email: 2421049459@qq.com
Project-URL: Bug Tracker, https://github.com/JasonloveDL/pyIAAS/issues
Classifier: Programming Language :: Python :: 3
Classifier: License :: OSI Approved :: GNU Affero General Public License v3
Classifier: Operating System :: OS Independent
Classifier: Development Status :: 3 - Alpha
Requires-Python: >=3.6
License-File: LICENSE
Requires-Dist: numpy
Requires-Dist: pandas
Requires-Dist: torch
Requires-Dist: torchaudio
Requires-Dist: torchvision
Requires-Dist: gym
Requires-Dist: matplotlib
Requires-Dist: clickconcurrent-log-handler
